aliyun_sls_logger/__init__.py
aliyun_sls_logger/auth.py
aliyun_sls_logger/log_logs_raw.proto
aliyun_sls_logger/log_logs_raw_pb2.py
aliyun_sls_logger/logclient.py
aliyun_sls_logger/logexception.py
aliyun_sls_logger/logger_handler.py
aliyun_sls_logger/logitem.py
aliyun_sls_logger/logrequest.py
aliyun_sls_logger/logresponse.py
aliyun_sls_logger/putlogsrequest.py
aliyun_sls_logger/putlogsresponse.py
aliyun_sls_logger/stream_util.py
aliyun_sls_logger/util.py
aliyun_sls_logger/version.py
aliyun_sls_logger-0.3.0.dist-info/METADATA
aliyun_sls_logger-0.3.0.dist-info/WHEEL
aliyun_sls_logger-0.3.0.dist-info/RECORD
