Metadata-Version: 2.1
Name: aliyun-sls-logger
Version: 0.3.0
Summary: async aliyun sls logger
Author: JimZhang
Author-email: zzl22100048@gmail.com
Requires-Python: >=3.9,<4.0
Classifier: Programming Language :: Python :: 3
Classifier: Programming Language :: Python :: 3.9
Classifier: Programming Language :: Python :: 3.10
Classifier: Programming Language :: Python :: 3.11
Requires-Dist: aiologger (>=0.7.0,<0.8.0)
Requires-Dist: aiostream (>=0.4.5,<0.5.0)
Requires-Dist: cramjam (>=2.7.0,<3.0.0)
Requires-Dist: httpx (>=0.24.1,<0.25.0)
Requires-Dist: orjson (>=3.9.6,<4.0.0)
Requires-Dist: protobuf (==3.20.3)
Requires-Dist: six (>=1.16.0,<2.0.0)
